{
  "@context": {
    "dcterms": "http://purl.org/dc/terms/",
    "geo": "http://www.opengis.net/ont/geosparql#",
    "owl": "http://www.w3.org/2002/07/owl#",
    "ps": "http://www.wikidata.org/prop/statement/",
    "rdf": "http://www.w3.org/1999/02/22-rdf-syntax-ns#",
    "rdfs": "http://www.w3.org/2000/01/rdf-schema#",
    "ri": "https://vwestric.github.io/regesta/",
    "wd": "http://www.wikidata.org/entity/",
    "xsd": "http://www.w3.org/2001/XMLSchema#"
  },
  "@graph": [
    {
      "@id": "ri:1466-09-18_2_0_13_22_0_137_137",
      "@type": "wd:Q1933248",
      "dcterms:source": {
        "@id": "_:Nae85eae62a2d4f5ca17aa55d47d63c7d"
      }
    },
    {
      "@id": "_:Nae85eae62a2d4f5ca17aa55d47d63c7d",
      "@type": "wd:Q49848",
      "dcterms:issued": {
        "@id": "_:N32da5d64a33a429cb6e0ca77c94d3d70"
      },
      "ps:P291": {
        "@id": "_:Nfedb38ccf7d643e09cd5a6c2a63e10a0"
      },
      "ps:P3342": {
        "@id": "_:N3a547b737cb24f9295d29bcaf6ca4c27"
      }
    },
    {
      "@id": "_:Nfedb38ccf7d643e09cd5a6c2a63e10a0",
      "https://schema.org#geo": {
        "@id": "_:N5c0e5d55c7994a5c8c41aec01a1e19d1"
      },
      "owl:sameAs": {
        "@id": "wd:Q13298"
      },
      "rdfs:label": "Graz"
    },
    {
      "@id": "_:N5c0e5d55c7994a5c8c41aec01a1e19d1",
      "@type": "https://schema.org#GeoCoordinates",
      "https://schema.org#latitude": "47.06667",
      "https://schema.org#longitude": "15.45"
    },
    {
      "@id": "_:N32da5d64a33a429cb6e0ca77c94d3d70",
      "@type": "dcterms:PeriodOfTime",
      "ps:P580": {
        "@type": "xsd:date",
        "@value": "1466-09-18"
      },
      "ps:P582": {
        "@type": "xsd:date",
        "@value": "1466-09-18"
      }
    },
    {
      "@id": "_:N3a547b737cb24f9295d29bcaf6ca4c27",
      "@type": "wd:Q5",
      "owl:sameAs": {
        "@id": "ri:O00000622"
      },
      "ps:P39": {
        "@id": "ri:herzog"
      },
      "rdfs:label": "Hz. Sigmund von Österreich"
    }
  ]
}