{
  "@context": {
    "dcterms": "http://purl.org/dc/terms/",
    "geo": "http://www.opengis.net/ont/geosparql#",
    "owl": "http://www.w3.org/2002/07/owl#",
    "ps": "http://www.wikidata.org/prop/statement/",
    "rdf": "http://www.w3.org/1999/02/22-rdf-syntax-ns#",
    "rdfs": "http://www.w3.org/2000/01/rdf-schema#",
    "ri": "https://vwestric.github.io/regesta/",
    "wd": "http://www.wikidata.org/entity/",
    "xsd": "http://www.w3.org/2001/XMLSchema#"
  },
  "@graph": [
    {
      "@id": "ri:1456-07-26_3_0_13_28_0_39_39",
      "@type": "wd:Q1933248",
      "dcterms:source": {
        "@id": "_:N89facac4d42a45468d6e51adeee35844"
      }
    },
    {
      "@id": "_:N89facac4d42a45468d6e51adeee35844",
      "@type": "wd:Q49848",
      "dcterms:issued": {
        "@id": "_:N73982e724aee4e6588db8873e9b32223"
      },
      "ps:P291": {
        "@id": "_:Nc1e65254b4dc49d990d9e93b6f17b8f3"
      },
      "ps:P3342": {
        "@id": "_:N570dbdf40e5048a3a8087754fe0bb72c"
      }
    },
    {
      "@id": "_:Nc1e65254b4dc49d990d9e93b6f17b8f3",
      "https://schema.org#geo": {
        "@id": "_:N4bc5ddf916144918b0c73fd1f2ccfd71"
      },
      "owl:sameAs": {
        "@id": "wd:Q131612"
      },
      "rdfs:label": "Wiener Neustadt"
    },
    {
      "@id": "_:N4bc5ddf916144918b0c73fd1f2ccfd71",
      "@type": "https://schema.org#GeoCoordinates",
      "https://schema.org#latitude": "47.813153",
      "https://schema.org#longitude": "16.24444"
    },
    {
      "@id": "_:N73982e724aee4e6588db8873e9b32223",
      "@type": "dcterms:PeriodOfTime",
      "ps:P580": {
        "@type": "xsd:date",
        "@value": "1456-07-26"
      },
      "ps:P582": {
        "@type": "xsd:date",
        "@value": "1456-07-26"
      }
    },
    {
      "@id": "_:N570dbdf40e5048a3a8087754fe0bb72c",
      "@type": "wd:Q5",
      "owl:sameAs": {
        "@id": "ri:B00002248"
      },
      "ps:P39": {
        "@id": "ri:markgraf"
      },
      "rdfs:label": "Mgf. Albrecht von Brandenburg"
    }
  ]
}