{
  "@context": {
    "dcterms": "http://purl.org/dc/terms/",
    "geo": "http://www.opengis.net/ont/geosparql#",
    "owl": "http://www.w3.org/2002/07/owl#",
    "ps": "http://www.wikidata.org/prop/statement/",
    "rdf": "http://www.w3.org/1999/02/22-rdf-syntax-ns#",
    "rdfs": "http://www.w3.org/2000/01/rdf-schema#",
    "ri": "https://vwestric.github.io/regesta/",
    "wd": "http://www.wikidata.org/entity/",
    "xsd": "http://www.w3.org/2001/XMLSchema#"
  },
  "@graph": [
    {
      "@id": "ri:1492-10-16_1_0_13_26_0_801_801",
      "@type": "wd:Q1933248",
      "dcterms:source": {
        "@id": "_:Ne7dede28671e4f72a423be3830aa455c"
      }
    },
    {
      "@id": "_:Ne7dede28671e4f72a423be3830aa455c",
      "@type": "wd:Q49848",
      "dcterms:issued": {
        "@id": "_:N092e1f6f0e9b4a7ebfd56f96bea46604"
      },
      "ps:P291": {
        "@id": "_:N71927d35c4db4aa98c064d6a41a0e622"
      }
    },
    {
      "@id": "_:N71927d35c4db4aa98c064d6a41a0e622",
      "https://schema.org#geo": {
        "@id": "_:Nf5c6d64b179f4275831d262c7a26fdb4"
      },
      "owl:sameAs": {
        "@id": "wd:Q41329"
      },
      "rdfs:label": "Linz"
    },
    {
      "@id": "_:Nf5c6d64b179f4275831d262c7a26fdb4",
      "@type": "https://schema.org#GeoCoordinates",
      "https://schema.org#latitude": "48.303056",
      "https://schema.org#longitude": "14.290556"
    },
    {
      "@id": "_:N092e1f6f0e9b4a7ebfd56f96bea46604",
      "@type": "dcterms:PeriodOfTime",
      "ps:P580": {
        "@type": "xsd:date",
        "@value": "1492-10-16"
      },
      "ps:P582": {
        "@type": "xsd:date",
        "@value": "1492-10-16"
      }
    }
  ]
}