{
  "@context": {
    "dcterms": "http://purl.org/dc/terms/",
    "geo": "http://www.opengis.net/ont/geosparql#",
    "owl": "http://www.w3.org/2002/07/owl#",
    "ps": "http://www.wikidata.org/prop/statement/",
    "rdf": "http://www.w3.org/1999/02/22-rdf-syntax-ns#",
    "rdfs": "http://www.w3.org/2000/01/rdf-schema#",
    "ri": "https://vwestric.github.io/regesta/",
    "wd": "http://www.wikidata.org/entity/",
    "xsd": "http://www.w3.org/2001/XMLSchema#"
  },
  "@graph": [
    {
      "@id": "ri:b117f365-b41a-4160-941d-a76bbaa3856d",
      "@type": "wd:Q1933248",
      "dcterms:source": {
        "@id": "_:N22e5ceff90d940e1b10e496da248797e"
      }
    },
    {
      "@id": "_:N22e5ceff90d940e1b10e496da248797e",
      "@type": "wd:Q49848",
      "dcterms:issued": {
        "@id": "_:Nb798589d08334bf5838dde8258683db2"
      },
      "ps:P291": {
        "@id": "_:N1dca23457e0a4507a229f91c08832342"
      },
      "ps:P3342": {
        "@id": "_:N59a3449503934465b3442d0d3ef2a7e7"
      }
    },
    {
      "@id": "_:N1dca23457e0a4507a229f91c08832342",
      "https://schema.org#geo": {
        "@id": "_:Nf99574de8ce1455483cf329be92bb279"
      },
      "owl:sameAs": {
        "@id": "wd:Q365"
      },
      "rdfs:label": "Köln"
    },
    {
      "@id": "_:Nf99574de8ce1455483cf329be92bb279",
      "@type": "https://schema.org#GeoCoordinates",
      "https://schema.org#latitude": "50.93333",
      "https://schema.org#longitude": "6.95"
    },
    {
      "@id": "_:Nb798589d08334bf5838dde8258683db2",
      "@type": "dcterms:PeriodOfTime",
      "ps:P580": {
        "@type": "xsd:date",
        "@value": "1486-04-28"
      },
      "ps:P582": {
        "@type": "xsd:date",
        "@value": "1486-04-28"
      }
    },
    {
      "@id": "_:N59a3449503934465b3442d0d3ef2a7e7",
      "@type": "wd:Q5",
      "owl:sameAs": {
        "@id": "ri:O00000622"
      },
      "ps:P39": {
        "@id": "ri:erzherzog"
      },
      "rdfs:label": "Ehz. Sigmund von Österreich"
    }
  ]
}