{
  "@context": {
    "dcterms": "http://purl.org/dc/terms/",
    "geo": "http://www.opengis.net/ont/geosparql#",
    "owl": "http://www.w3.org/2002/07/owl#",
    "ps": "http://www.wikidata.org/prop/statement/",
    "rdf": "http://www.w3.org/1999/02/22-rdf-syntax-ns#",
    "rdfs": "http://www.w3.org/2000/01/rdf-schema#",
    "ri": "https://vwestric.github.io/regesta/",
    "wd": "http://www.wikidata.org/entity/",
    "xsd": "http://www.w3.org/2001/XMLSchema#"
  },
  "@graph": [
    {
      "@id": "ri:1442-06-17_2_0_13_6_0_10992_14",
      "@type": "wd:Q1933248",
      "dcterms:source": {
        "@id": "_:Nf6d6b36e27a94833b9a75586c3280262"
      }
    },
    {
      "@id": "_:Nf6d6b36e27a94833b9a75586c3280262",
      "@type": "wd:Q49848",
      "dcterms:issued": {
        "@id": "_:N3e803248b67c4eb09072aa2cc95199f6"
      },
      "ps:P291": {
        "@id": "_:N951651ba671948569fee17f5b7bcb1e5"
      },
      "ps:P3342": {
        "@id": "_:N53e50e4b8fd04043910bbbc4b79ff88e"
      }
    },
    {
      "@id": "_:N951651ba671948569fee17f5b7bcb1e5",
      "https://schema.org#geo": {
        "@id": "_:Nd2bc7fe47b7c42169c89d16b50821753"
      },
      "owl:sameAs": {
        "@id": "wd:Q1017"
      },
      "rdfs:label": "Aachen"
    },
    {
      "@id": "_:Nd2bc7fe47b7c42169c89d16b50821753",
      "@type": "https://schema.org#GeoCoordinates",
      "https://schema.org#latitude": "50.77664",
      "https://schema.org#longitude": "6.08342"
    },
    {
      "@id": "_:N3e803248b67c4eb09072aa2cc95199f6",
      "@type": "dcterms:PeriodOfTime",
      "ps:P580": {
        "@type": "xsd:date",
        "@value": "1442-06-17"
      },
      "ps:P582": {
        "@type": "xsd:date",
        "@value": "1442-06-17"
      }
    },
    {
      "@id": "_:N53e50e4b8fd04043910bbbc4b79ff88e",
      "@type": "wd:Q5",
      "owl:sameAs": {
        "@id": "ri:O00000622"
      },
      "ps:P39": {
        "@id": "ri:herzog"
      },
      "rdfs:label": "Hz. Sigmund von Österreich"
    }
  ]
}