{
  "@context": {
    "dcterms": "http://purl.org/dc/terms/",
    "geo": "http://www.opengis.net/ont/geosparql#",
    "owl": "http://www.w3.org/2002/07/owl#",
    "ps": "http://www.wikidata.org/prop/statement/",
    "rdf": "http://www.w3.org/1999/02/22-rdf-syntax-ns#",
    "rdfs": "http://www.w3.org/2000/01/rdf-schema#",
    "ri": "https://vwestric.github.io/regesta/",
    "wd": "http://www.wikidata.org/entity/",
    "xsd": "http://www.w3.org/2001/XMLSchema#"
  },
  "@graph": [
    {
      "@id": "ri:1479-03-30_1_0_13_29_0_212_212",
      "@type": "wd:Q1933248",
      "dcterms:source": {
        "@id": "_:Na50be7abff294bd7a08c0b359134a69b"
      }
    },
    {
      "@id": "_:Na50be7abff294bd7a08c0b359134a69b",
      "@type": "wd:Q49848",
      "dcterms:issued": {
        "@id": "_:Nbf1be6c0905b4f2995d33e555b272264"
      },
      "ps:P291": {
        "@id": "_:N60b67f9c53774accb3e139dd2c4b2dfd"
      }
    },
    {
      "@id": "_:N60b67f9c53774accb3e139dd2c4b2dfd",
      "https://schema.org#geo": {
        "@id": "_:Nb85f944864144445b0841c844c67333a"
      },
      "owl:sameAs": {
        "@id": "wd:Q13298"
      },
      "rdfs:label": "Graz"
    },
    {
      "@id": "_:Nb85f944864144445b0841c844c67333a",
      "@type": "https://schema.org#GeoCoordinates",
      "https://schema.org#latitude": "47.06667",
      "https://schema.org#longitude": "15.45"
    },
    {
      "@id": "_:Nbf1be6c0905b4f2995d33e555b272264",
      "@type": "dcterms:PeriodOfTime",
      "ps:P580": {
        "@type": "xsd:date",
        "@value": "1479-03-30"
      },
      "ps:P582": {
        "@type": "xsd:date",
        "@value": "1479-03-30"
      }
    }
  ]
}