{
  "@context": {
    "dcterms": "http://purl.org/dc/terms/",
    "geo": "http://www.opengis.net/ont/geosparql#",
    "owl": "http://www.w3.org/2002/07/owl#",
    "ps": "http://www.wikidata.org/prop/statement/",
    "rdf": "http://www.w3.org/1999/02/22-rdf-syntax-ns#",
    "rdfs": "http://www.w3.org/2000/01/rdf-schema#",
    "ri": "https://vwestric.github.io/regesta/",
    "wd": "http://www.wikidata.org/entity/",
    "xsd": "http://www.w3.org/2001/XMLSchema#"
  },
  "@graph": [
    {
      "@id": "ri:1469-09-04_3_0_13_5_0_10821_197",
      "@type": "wd:Q1933248",
      "dcterms:source": {
        "@id": "_:Nea51432b37e247e8ad620ec4e75086a2"
      }
    },
    {
      "@id": "_:Nea51432b37e247e8ad620ec4e75086a2",
      "@type": "wd:Q49848",
      "dcterms:issued": {
        "@id": "_:N4ca005207c21437fa855e828f18a0b23"
      },
      "ps:P291": {
        "@id": "_:N659167df4def489e8a00cfeb29564d15"
      },
      "ps:P3342": [
        {
          "@id": "_:N863ea683522d4db39ac0a9a3e3f259ca"
        },
        {
          "@id": "_:N52681b998c0a4f01b9124680dc791300"
        }
      ]
    },
    {
      "@id": "_:N659167df4def489e8a00cfeb29564d15",
      "https://schema.org#geo": {
        "@id": "_:N0e7da82b3fee444ebcee12cf7c907efc"
      },
      "owl:sameAs": {
        "@id": "wd:Q131612"
      },
      "rdfs:label": "Wiener Neustadt"
    },
    {
      "@id": "_:N0e7da82b3fee444ebcee12cf7c907efc",
      "@type": "https://schema.org#GeoCoordinates",
      "https://schema.org#latitude": "47.813153",
      "https://schema.org#longitude": "16.24444"
    },
    {
      "@id": "_:N4ca005207c21437fa855e828f18a0b23",
      "@type": "dcterms:PeriodOfTime",
      "ps:P580": {
        "@type": "xsd:date",
        "@value": "1469-09-04"
      },
      "ps:P582": {
        "@type": "xsd:date",
        "@value": "1469-09-04"
      }
    },
    {
      "@id": "_:N863ea683522d4db39ac0a9a3e3f259ca",
      "@type": "wd:Q5",
      "owl:sameAs": {
        "@id": "ri:P00001036"
      },
      "ps:P39": {
        "@id": "ri:pfalzgraf"
      },
      "rdfs:label": "Pfgf. Ludwig von (Zweibrücken-)Veldenz"
    },
    {
      "@id": "_:N52681b998c0a4f01b9124680dc791300",
      "@type": "wd:Q5",
      "owl:sameAs": {
        "@id": "ri:S00001247"
      },
      "rdfs:label": "Johann von Scharfenstein"
    }
  ]
}